graphene_elastic/__init__.py
graphene_elastic/advanced_types.py
graphene_elastic/arrayconnection.py
graphene_elastic/compat.py
graphene_elastic/constants.py
graphene_elastic/converter.py
graphene_elastic/enums.py
graphene_elastic/exceptions.py
graphene_elastic/fields.py
graphene_elastic/logging.py
graphene_elastic/registry.py
graphene_elastic/settings.py
graphene_elastic/utils.py
graphene_elastic/versions.py
graphene_elastic/filter_backends/__init__.py
graphene_elastic/filter_backends/base.py
graphene_elastic/filter_backends/queries.py
graphene_elastic/filter_backends/faceted_search/__init__.py
graphene_elastic/filter_backends/faceted_search/common.py
graphene_elastic/filter_backends/filtering/__init__.py
graphene_elastic/filter_backends/filtering/common.py
graphene_elastic/filter_backends/filtering/mixins.py
graphene_elastic/filter_backends/filtering/queries.py
graphene_elastic/filter_backends/highlight/__init__.py
graphene_elastic/filter_backends/highlight/common.py
graphene_elastic/filter_backends/ordering/__init__.py
graphene_elastic/filter_backends/ordering/common.py
graphene_elastic/filter_backends/post_filter/__init__.py
graphene_elastic/filter_backends/post_filter/common.py
graphene_elastic/filter_backends/score/__init__.py
graphene_elastic/filter_backends/score/common.py
graphene_elastic/filter_backends/search/__init__.py
graphene_elastic/filter_backends/search/base.py
graphene_elastic/filter_backends/search/common.py
graphene_elastic/filter_backends/search/compound.py
graphene_elastic/filter_backends/search/query_string.py
graphene_elastic/filter_backends/search/simple_query_string.py
graphene_elastic/filter_backends/search/query_backends/__init__.py
graphene_elastic/filter_backends/search/query_backends/base.py
graphene_elastic/filter_backends/search/query_backends/match.py
graphene_elastic/filter_backends/search/query_backends/match_phrase.py
graphene_elastic/filter_backends/search/query_backends/match_phrase_prefix.py
graphene_elastic-0.8.1.dist-info/LICENSE_GPL2.0.txt
graphene_elastic-0.8.1.dist-info/LICENSE_LGPL_2.1.txt
graphene_elastic-0.8.1.dist-info/METADATA
graphene_elastic-0.8.1.dist-info/WHEEL
graphene_elastic-0.8.1.dist-info/top_level.txt
graphene_elastic-0.8.1.dist-info/zip-safe
graphene_elastic-0.8.1.dist-info/RECORD
