Metadata-Version: 2.1
Name: graphene-elastic
Version: 0.8.1
Summary: Graphene Elasticsearch/OpenSearch (DSL) integration
Home-page: https://github.com/barseghyanartur/graphene-elastic
Author: Artur Barseghyan
Author-email: artur.barseghyan@gmail.com
License: GPL 2.0/LGPL 2.1
Project-URL: Bug Tracker, https://github.com/barseghyanartur/graphene-elastic/issues
Project-URL: Documentation, https://graphene-elastic.readthedocs.io/
Project-URL: Source Code, https://github.com/barseghyanartur/graphene-elastic/
Project-URL: Changelog, https://graphene-elastic.readthedocs.io/en/latest/changelog.html
Keywords: api graphql protocol rest relay graphene anysearch elasticsearch elasticsearch-dsl opensearch opensearch-dsl
Classifier: Development Status :: 4 - Beta
Classifier: Intended Audience :: Developers
Classifier: Topic :: Software Development :: Libraries
Classifier: Programming Language :: Python :: 3.6
Classifier: Programming Language :: Python :: 3.7
Classifier: Programming Language :: Python :: 3.8
Classifier: Programming Language :: Python :: 3.9
Classifier: Programming Language :: Python :: 3.10
Requires-Python: >=3.6
License-File: LICENSE_GPL2.0.txt
License-File: LICENSE_LGPL_2.1.txt
Requires-Dist: graphene <3,>=2.1.3
Requires-Dist: singledispatch >=3.4.0.3
Requires-Dist: iso8601 >=0.1.12
Requires-Dist: stringcase
Requires-Dist: anysearch >=0.2.1
Requires-Dist: typing ; python_version < "3.7"
Provides-Extra: elasticsearch
Requires-Dist: elasticsearch >=6.0 ; extra == 'elasticsearch'
Requires-Dist: elasticsearch-dsl <8.0,>=6.0 ; extra == 'elasticsearch'
Provides-Extra: opensearch
Requires-Dist: opensearch-py ; extra == 'opensearch'
Requires-Dist: opensearch-dsl ; extra == 'opensearch'
